mult_32.v
module mult_32(clk, rst, init, A, B, pp, done);
    input rst;
    input clk;
    input init;
    input [15:0] A;
    input [15:0] B;

    output [31:0] pp;
    output done;

    wire w_sh;
    wire w_reset;
    wire w_add;
    wire w_z;

    wire [31:0] w_A;
    wire [15:0] w_B;
    
    // Instancias de módulos
    rsr rsr0 (.clk(clk), .in_B(B), .shift(w_sh), .load(w_reset), .s_B(w_B));
    lsr lsr0 (.clk(clk), .in_A(A), .shift(w_sh), .load(w_reset), .s_A(w_A));
    comp comp0(.B(w_B), .z(w_z));
    acc acc0 (.clk(clk), .A(w_A), .add(w_add), .rst(w_reset), .pp(pp));
    
    // Corregido: .done(done) con el punto inicial
    control_mult control0 (
        .clk(clk), .rst(rst), .lsb_B(w_B[0]), .init(init), .z(w_z), 
        .done(done), .sh(w_sh), .reset(w_reset), .add(w_add)
    );

endmodule

// --- Módulo RSR ---
module rsr (clk, in_B, shift, load, s_B);
    input clk;
    input [15:0] in_B;
    input load;
    input shift;
    output reg [15:0] s_B;
    
    always @(negedge clk) begin
        if(load)
            s_B <= in_B;
        else if(shift)
            s_B <= s_B >> 1;
    end
endmodule
    
// --- Módulo LSR ---
module lsr (clk, in_A, shift, load, s_A);
    input clk;
    input [15:0] in_A;
    input load;
    input shift;
    output reg [31:0] s_A; // Corregido de 30 a 31 (bus de 32 bits)
    
    always @(negedge clk) begin
        if(load)
            s_A <= {16'b0, in_A}; // Carga con extensión de ceros
        else if(shift)
            s_A <= s_A << 1;
    end
endmodule

// --- Módulo Comparador ---
module comp(B, z);
    input [15:0] B;
    output z;

    assign z = (B == 16'b0) ? 1'b1 : 1'b0;
endmodule

// --- Módulo Acumulador ---
module acc (clk, A, add, rst, pp);
    input clk;
    input [31:0] A;
    input add;
    input rst;
    output reg [31:0] pp;

    initial pp = 0;

    always @(negedge clk) begin
        if (rst)
            pp <= 32'h00000000;
        else if (add)
            pp <= pp + A;
    end
endmodule

// --- Módulo Controlador ---
module control_mult(clk, rst, lsb_B, init, z, done, sh, reset, add);
    input clk, rst, lsb_B, init, z;
    output reg done, sh, reset, add;

    parameter START = 3'b000;
    parameter CHECK = 3'b001;
    parameter SHIFT = 3'b010;
    parameter ADD   = 3'b011;
    parameter END   = 3'b100;

    reg [2:0] state;
    reg [3:0] count;

    initial begin
        done = 0; sh = 0; reset = 0; add = 0;
        state = START;
        count = 0;
    end

    // Lógica de Siguiente Estado
    always @(posedge clk) begin
        if (rst) begin
            state <= START;
        end else begin
            case(state)
                START: begin
                    count <= 0;
                    if(init) state <= CHECK;
                    else     state <= START;
                end

                CHECK: begin
                    if(lsb_B) state <= ADD;
                    else      state <= SHIFT;
                end

                SHIFT: begin
                    if(z) state <= END;
                    else  state <= CHECK;
                end

                ADD: begin
                    state <= SHIFT;
                end

                END: begin
                    count <= count + 1;
                    state <= (count > 9) ? START : END;
                end 

                default: state <= START;
            endcase  
        end
    end 

    // Lógica de Salidas (Combinacional)
    always @(state) begin
        case(state)
            START: begin
                done = 0; sh = 0; reset = 1; add = 0;
            end
            CHECK: begin
                done = 0; sh = 0; reset = 0; add = 0;
            end
            SHIFT: begin
                done = 0; sh = 1; reset = 0; add = 0;
            end
            ADD: begin
                done = 0; sh = 0; reset = 0; add = 1;
            end
            END: begin
                done = 1; sh = 0; reset = 0; add = 0;
            end
            default: begin
                done = 0; sh = 0; reset = 0; add = 0;
            end
        endcase
    end
endmodule

mult_32_TB.v
`timescale 1ns / 1ps

module mult_32_TB;
    // 1. Declarar señales para conectar al multiplicador
    reg clk;
    reg rst;
    reg init;
    reg [15:0] A;
    reg [15:0] B;
    wire [31:0] pp;
    wire done;

    // 2. Instanciar la Unidad Bajo Prueba (UUT)
    mult_32 uut (
        .clk(clk), 
        .rst(rst), 
        .init(init), 
        .A(A), 
        .B(B), 
        .pp(pp), 
        .done(done)
    );

    // 3. Generar el Reloj (oscila cada 10 unidades de tiempo)
    always #10 clk = ~clk;

    initial begin
        // Configuración inicial para ver ondas en Linux
        $dumpfile("simulacion.vcd"); // Archivo para GTKWave
        $dumpvars(0, mult_32_TB);

        // Inicializar señales
        clk = 0;
        rst = 1;
        init = 0;
        A = 0;
        B = 0;

        // Resetear el sistema
        #25 rst = 0;
        
        // --- PRUEBA 1: 5 x 3 ---
        #20;
        A = 16'd5;
        B = 16'd3;
        init = 1;      // Pulso de inicio
        #20 init = 0;

        // Esperar a que termine (hasta que done sea 1)
        wait(done);
        
        // --- PRUEBA 2: 10 x 10 ---
        #100;
        A = 16'd10;
        B = 16'd10;
        init = 1;
        #20 init = 0;
        
        wait(done);

        #100;
        $display("Simulacion finalizada. Revisa las ondas.");
        $finish;
    end
endmodule

simulacion.vcd
$date
	Sat Apr 18 23:35:04 2026
$end
$version
	Icarus Verilog
$end
$timescale
	1ps
$end
$scope module mult_32_TB $end
$var wire 32 ! pp [31:0] $end
$var wire 1 " done $end
$var reg 16 # A [15:0] $end
$var reg 16 $ B [15:0] $end
$var reg 1 % clk $end
$var reg 1 & init $end
$var reg 1 ' rst $end
$scope module uut $end
$var wire 16 ( A [15:0] $end
$var wire 16 ) B [15:0] $end
$var wire 1 % clk $end
$var wire 1 & init $end
$var wire 1 ' rst $end
$var wire 1 * w_z $end
$var wire 1 + w_sh $end
$var wire 1 , w_reset $end
$var wire 1 - w_add $end
$var wire 16 . w_B [15:0] $end
$var wire 32 / w_A [31:0] $end
$var wire 32 0 pp [31:0] $end
$var wire 1 " done $end
$scope module acc0 $end
$var wire 1 % clk $end
$var wire 1 , rst $end
$var wire 1 - add $end
$var wire 32 1 A [31:0] $end
$var reg 32 2 pp [31:0] $end
$upscope $end
$scope module comp0 $end
$var wire 1 * z $end
$var wire 16 3 B [15:0] $end
$upscope $end
$scope module control0 $end
$var wire 1 % clk $end
$var wire 1 & init $end
$var wire 1 4 lsb_B $end
$var wire 1 ' rst $end
$var wire 1 * z $end
$var parameter 3 5 ADD $end
$var parameter 3 6 CHECK $end
$var parameter 3 7 END $end
$var parameter 3 8 SHIFT $end
$var parameter 3 9 START $end
$var reg 1 - add $end
$var reg 4 : count [3:0] $end
$var reg 1 " done $end
$var reg 1 , reset $end
$var reg 1 + sh $end
$var reg 3 ; state [2:0] $end
$upscope $end
$scope module lsr0 $end
$var wire 1 % clk $end
$var wire 16 < in_A [15:0] $end
$var wire 1 , load $end
$var wire 1 + shift $end
$var reg 32 = s_A [31:0] $end
$upscope $end
$scope module rsr0 $end
$var wire 1 % clk $end
$var wire 16 > in_B [15:0] $end
$var wire 1 , load $end
$var wire 1 + shift $end
$var reg 16 ? s_B [15:0] $end
$upscope $end
$upscope $end
$upscope $end
$enddefinitions $end
$comment Show the parameter values. $end
$dumpall
b0 9
b10 8
b100 7
b1 6
b11 5
$end
#0
$dumpvars
b0 ?
b0 >
b0 =
b0 <
b0 ;
b0 :
04
b0 3
b0 2
b0 1
b0 0
b0 /
b0 .
0-
1,
0+
1*
b0 )
b0 (
1'
0&
0%
b0 $
b0 #
0"
b0 !
$end
#10000
1%
#20000
0%
#25000
0'
#30000
1%
#40000
0%
#45000
1&
b11 $
b11 )
b11 >
b101 #
b101 (
b101 <
#50000
0,
b1 ;
1%
#60000
0%
#65000
0&
#70000
1+
b10 ;
1%
#80000
0%
#90000
0+
1"
b100 ;
1%
#100000
0%
#110000
b1 :
1%
#120000
0%
#130000
b10 :
1%
#140000
0%
#150000
b11 :
1%
#160000
0%
#170000
b100 :
1%
#180000
0%
#190000
b101 :
1%
1&
b1010 $
b1010 )
b1010 >
b1010 #
b1010 (
b1010 <
#200000
0%
#210000
b110 :
1%
0&
#220000
0%
#230000
b111 :
1%
#240000
0%
#250000
b1000 :
1%
#260000
0%
#270000
b1001 :
1%
#280000
0%
#290000
b1010 :
1%
#300000
0%
#310000
1,
0"
b0 ;
b1011 :
1%
